multiscale_actin/__init__.py
multiscale_actin/composites/__init__.py
multiscale_actin/composites/template_composite.py
multiscale_actin/experiments/__init__.py
multiscale_actin/library/__init__.py
multiscale_actin/processes/__init__.py
multiscale_actin/processes/readdy_actin_membrane.py
multiscale_actin/processes/simularium_emitter.py
multiscale_actin-1.1.0.dist-info/licenses/LICENSE
multiscale_actin-1.1.0.dist-info/METADATA
multiscale_actin-1.1.0.dist-info/WHEEL
multiscale_actin-1.1.0.dist-info/top_level.txt
multiscale_actin-1.1.0.dist-info/RECORD
